{
  "type": "Feature",
  "properties": {
    "gn:country":"NA",
    "gn:fcode":"RESW",
    "gn:population":150,
    "iso:country":"NA",
    "qs:name":"Erindi",
    "qs:photos_9r":0,
    "qs:photos_sr":0,
    "qs:pop_sr":"1",
    "wof:name":"Erindi",
    "wof:placetype":"locality",
    "wof:population":150
},
  "geometry": {"coordinates":[16.38718,-21.5459],"type":"Point"}
}