{
  "type": "Feature",
  "properties": {
    "iso:country":"NA",
    "name:dut_x_preferred":[
        "Windhoek West"
    ],
    "name:eng_x_preferred":[
        "Windhoek West"
    ],
    "name:ger_x_preferred":[
        "Windhoek-West"
    ],
    "name:ita_x_preferred":[
        "Windhoek Ovest"
    ],
    "name:spa_x_preferred":[
        "Windhoek Oeste"
    ],
    "qs:gn_pop":0,
    "qs:name":"Windhoek West",
    "qs:name_adm0":"Namibia",
    "qs:name_adm1":"Khomas",
    "qs:photos":213,
    "qs:photos_1k":43,
    "qs:photos_9k":1,
    "qs:photos_9r":4,
    "qs:photos_all":213,
    "qs:photos_sr":4,
    "qs:placetype":"Town",
    "qs:pop_sr":"0",
    "qs:woe_adm0":23424987,
    "wof:name":"Windhoek West",
    "wof:placetype":"locality"
},
  "geometry": {"coordinates":[17.077732,-22.567335],"type":"Point"}
}