{
  "type": "Feature",
  "properties": {
    "iso:country":"NA",
    "name:afr_x_preferred":[
        "Khorixas"
    ],
    "name:ast_x_preferred":[
        "Khorixas"
    ],
    "name:ceb_x_preferred":[
        "Khorixas"
    ],
    "name:dan_x_preferred":[
        "Khorixas"
    ],
    "name:deu_x_preferred":[
        "Khorixas"
    ],
    "name:eng_x_preferred":[
        "Khorixas"
    ],
    "name:fin_x_preferred":[
        "Khorixas"
    ],
    "name:fra_x_preferred":[
        "Khorixas"
    ],
    "name:ita_x_preferred":[
        "Khorixas"
    ],
    "name:mdf_x_preferred":[
        "\u0425\u043e\u0440\u0438\u043a\u0441\u0430\u0441"
    ],
    "name:nld_x_preferred":[
        "Khorixas"
    ],
    "name:pol_x_preferred":[
        "Khorixas"
    ],
    "name:por_x_preferred":[
        "Khorixas"
    ],
    "name:ron_x_preferred":[
        "Khorixas"
    ],
    "name:rus_x_preferred":[
        "\u041a\u0445\u043e\u0440\u0438\u0445\u0430\u0441"
    ],
    "name:spa_x_preferred":[
        "Khorixas"
    ],
    "name:swa_x_preferred":[
        "Khorixas"
    ],
    "name:und_x_variant":[
        "Welwitsch"
    ],
    "name:zho_x_preferred":[
        "\u970d\u91cc\u514b\u85a9\u65af"
    ],
    "name:zul_x_preferred":[
        "Khorixas"
    ],
    "qs:gn_country":"NA",
    "qs:gn_fcode":"PPL",
    "qs:gn_pop":12021,
    "qs:name":"Khorixas",
    "qs:name_adm0":"Namibia",
    "qs:name_adm1":"Kunene",
    "qs:photos":10,
    "qs:photos_1k":2,
    "qs:photos_9k":1,
    "qs:photos_9r":1,
    "qs:photos_all":10,
    "qs:photos_sr":1,
    "qs:placetype":"Town",
    "qs:pop_sr":"6",
    "qs:woe_adm0":23424987,
    "wd:wordcount":561,
    "wof:name":"Khorixas",
    "wof:placetype":"locality",
    "wof:population":12021
},
  "geometry": {"coordinates":[14.96667,-20.36667],"type":"Point"}
}