{
  "type": "Feature",
  "properties": {
    "gn:country":"NA",
    "gn:fcode":"PPLL",
    "gn:population":50,
    "iso:country":"NA",
    "qs:name":"Okashana Kelao",
    "qs:photos_9r":0,
    "qs:photos_sr":0,
    "qs:pop_sr":"1",
    "wof:name":"Okashana Kelao",
    "wof:placetype":"locality",
    "wof:population":50
},
  "geometry": {"coordinates":[16.65858,-18.24571],"type":"Point"}
}