{
  "type": "Feature",
  "properties": {
    "gn:country":"NA",
    "gn:fcode":"PPL",
    "gn:population":3430,
    "iso:country":"NA",
    "name:afr_x_preferred":[
        "Aranos"
    ],
    "name:bul_x_preferred":[
        "\u0410\u0440\u0430\u043d\u043e\u0441"
    ],
    "name:ceb_x_preferred":[
        "Aranos"
    ],
    "name:deu_x_preferred":[
        "Aranos"
    ],
    "name:eng_x_preferred":[
        "Aranos"
    ],
    "name:fin_x_preferred":[
        "Aranos"
    ],
    "name:ita_x_preferred":[
        "Aranos"
    ],
    "name:nld_x_preferred":[
        "Aranos"
    ],
    "name:pol_x_preferred":[
        "Aranos"
    ],
    "name:spa_x_preferred":[
        "Aranos"
    ],
    "name:swa_x_preferred":[
        "Aranos"
    ],
    "name:zul_x_preferred":[
        "Aranos"
    ],
    "qs:name":"Aranos",
    "qs:photos_9r":0,
    "qs:photos_sr":0,
    "qs:pop_sr":"4",
    "wd:wordcount":214,
    "wof:name":"Aranos",
    "wof:placetype":"locality",
    "wof:population":3430
},
  "geometry": {"coordinates":[19.11667,-24.13333],"type":"Point"}
}