{
  "type": "Feature",
  "properties": {
    "iso:country":"NA",
    "name:dut_x_preferred":[
        "Uis"
    ],
    "name:eng_x_preferred":[
        "Uis"
    ],
    "name:fre_x_preferred":[
        "Uis"
    ],
    "name:ger_x_preferred":[
        "Uis"
    ],
    "name:ita_x_preferred":[
        "Uis"
    ],
    "name:jpn_x_preferred":[
        "\u30a6\u30a4\u30b9"
    ],
    "name:rum_x_preferred":[
        "Uis"
    ],
    "name:slv_x_preferred":[
        "Uis"
    ],
    "name:spa_x_preferred":[
        "Uis"
    ],
    "name:unk_x_variant":[
        "Groot Uis"
    ],
    "qs:gn_country":"NA",
    "qs:gn_fcode":"PPL",
    "qs:gn_pop":0,
    "qs:name":"Uis",
    "qs:name_adm0":"Namibia",
    "qs:name_adm1":"Erongo",
    "qs:photos":6,
    "qs:photos_1k":1,
    "qs:photos_9k":1,
    "qs:photos_9r":1,
    "qs:photos_all":6,
    "qs:photos_sr":1,
    "qs:placetype":"Town",
    "qs:pop_sr":"5",
    "qs:woe_adm0":23424987,
    "wof:name":"Uis",
    "wof:placetype":"locality"
},
  "geometry": {"coordinates":[14.85,-21.21667],"type":"Point"}
}