{
  "type": "Feature",
  "properties": {
    "iso:country":"NA",
    "qs:gn_pop":0,
    "qs:name":"Tamariskia",
    "qs:name_adm0":"Namibia",
    "qs:name_adm1":"Erongo",
    "qs:photos":3,
    "qs:photos_1k":1,
    "qs:photos_9k":1,
    "qs:photos_9r":1,
    "qs:photos_all":3,
    "qs:photos_sr":1,
    "qs:placetype":"Town",
    "qs:pop_sr":"0",
    "qs:woe_adm0":23424987,
    "wof:name":"Tamariskia",
    "wof:placetype":"locality"
},
  "geometry": {"coordinates":[14.548108,-22.655881],"type":"Point"}
}