{
  "type": "Feature",
  "properties": {
    "iso:country":"NA",
    "name:deu_x_preferred":[
        "Helmeringhausen"
    ],
    "name:eng_x_preferred":[
        "Helmeringhausen"
    ],
    "name:nld_x_preferred":[
        "Helmeringhausen"
    ],
    "name:ron_x_preferred":[
        "Helmeringhausen"
    ],
    "qs:gn_country":"NA",
    "qs:gn_fcode":"PPL",
    "qs:gn_pop":0,
    "qs:name":"Helmeringhausen",
    "qs:name_adm0":"Namibia",
    "qs:name_adm1":"Karas",
    "qs:photos":21,
    "qs:photos_1k":4,
    "qs:photos_9k":1,
    "qs:photos_9r":1,
    "qs:photos_all":21,
    "qs:photos_sr":1,
    "qs:placetype":"Town",
    "qs:pop_sr":"4",
    "qs:woe_adm0":23424987,
    "wd:wordcount":142,
    "wof:name":"Helmeringhausen",
    "wof:placetype":"locality"
},
  "geometry": {"coordinates":[16.81667,-25.88333],"type":"Point"}
}